rubylang/__init__.py
rubylang/ruby_array.py
rubylang-0.0.3.dist-info/LICENSE
rubylang-0.0.3.dist-info/METADATA
rubylang-0.0.3.dist-info/WHEEL
rubylang-0.0.3.dist-info/RECORD
