Metadata-Version: 2.1
Name: rubylang
Version: 0.0.3
Summary: Ruby like objects in Python
Keywords: ruby,Array,Hash,String
Author: Sumanth
Author-email: sumanthreddystar@gmail.com
Requires-Python: >=3.11,<4.0
Classifier: Programming Language :: Python :: 3
Classifier: Programming Language :: Python :: 3.11
